pogoraidbot/__init__.py
pogoraidbot/__main__.py
pogoraidbot/version.py
pogoraidbot/bot/__init__.py
pogoraidbot/bot/about.py
pogoraidbot/bot/exceptions.py
pogoraidbot/cachedmethod/__init__.py
pogoraidbot/data/__init__.py
pogoraidbot/data/boss.py
pogoraidbot/data/data.py
pogoraidbot/data/gym.py
pogoraidbot/data/exceptions/__init__.py
pogoraidbot/exceptions/__init__.py
pogoraidbot/log/__init__.py
pogoraidbot/raid/__init__.py
pogoraidbot/redis_keys/__init__.py
pogoraidbot/screenshot/__init__.py
pogoraidbot/screenshot/resources.py
pogoraidbot-0.4.14.dist-info/LICENSE
pogoraidbot-0.4.14.dist-info/METADATA
pogoraidbot-0.4.14.dist-info/WHEEL
pogoraidbot-0.4.14.dist-info/top_level.txt
pogoraidbot-0.4.14.dist-info/RECORD
