Metadata-Version: 2.1
Name: pogoraidbot
Version: 0.4.14
Summary: A telegram bot to organize PoGo raid that it can be self hosted
Home-page: https://github.com/RobertoBochet/pogoraidbot
Author: Roberto Bochet
Author-email: robertobochet@gmail.com
License: gpl-3.0
Keywords: game,pokemongo,pogo,pokemongo-raid,telegram,telegrambot
Platform: UNKNOWN
Classifier: Development Status :: 4 - Beta
Classifier: Topic :: Scientific/Engineering :: Image Recognition
Classifier: Operating System :: OS Independent
Classifier: License :: OSI Approved :: GNU General Public License v3 (GPLv3)
Classifier: Programming Language :: Python :: 3
Requires-Python: >=3.6
Requires-Dist: python-telegram-bot (~=12.7)
Requires-Dist: opencv-python (~=4.1)
Requires-Dist: pytesseract (~=0.3)
Requires-Dist: redis (~=3.5)
Requires-Dist: requests (~=2.22)
Requires-Dist: schema (~=0.7)
Requires-Dist: apscheduler (~=3.6)
Requires-Dist: mpu (~=0.23)
